gradboard/__init__.py
gradboard/cycles.py
gradboard/optimiser.py
gradboard/scheduler.py
gradboard-6.2.0.dist-info/LICENSE
gradboard-6.2.0.dist-info/METADATA
gradboard-6.2.0.dist-info/WHEEL
gradboard-6.2.0.dist-info/RECORD
